sparkstrader/ApiClient.py
sparkstrader/__init__.py
sparkstrader/config.py
sparkstrader/Api/AuthApi.py
sparkstrader/Api/BaseApi.py
sparkstrader/Api/CrudApi.py
sparkstrader/Api/ExchangeApi.py
sparkstrader/Api/ExchangesApi.py
sparkstrader/Api/__init__.py
sparkstrader/Dto/CreateUpdateExchangeDto.py
sparkstrader/Dto/ExchangeDto.py
sparkstrader/Dto/PagedAndSortedResultRequestDto.py
sparkstrader/Dto/__init__.py
sparkstrader/Enums/Enums.py
sparkstrader/Enums/__init__.py
tests/__init__.py
tests/testApiClient.py
tests/test_Exchange.py
sparkstrader-0.0.1.dist-info/LICENSE
sparkstrader-0.0.1.dist-info/METADATA
sparkstrader-0.0.1.dist-info/WHEEL
sparkstrader-0.0.1.dist-info/top_level.txt
sparkstrader-0.0.1.dist-info/RECORD
